rotating_mitmproxy/__init__.py
rotating_mitmproxy/__main__.py
rotating_mitmproxy/cli.py
rotating_mitmproxy/config.py
rotating_mitmproxy/logging_addon.py
rotating_mitmproxy/monitoring.py
rotating_mitmproxy/server.py
rotating_mitmproxy/strategies.py
rotating_mitmproxy/thread_safe_rotator.py
rotating_mitmproxy-1.3.0.dist-info/licenses/LICENSE
rotating_mitmproxy-1.3.0.dist-info/METADATA
rotating_mitmproxy-1.3.0.dist-info/WHEEL
rotating_mitmproxy-1.3.0.dist-info/entry_points.txt
rotating_mitmproxy-1.3.0.dist-info/top_level.txt
rotating_mitmproxy-1.3.0.dist-info/RECORD
