Metadata-Version: 2.4
Name: rotating-mitmproxy
Version: 1.3.0
Summary: Smart proxy rotator built on mitmproxy with health monitoring and failover
Author-email: importal <xychen@msn.com>
Maintainer-email: importal <xychen@msn.com>
License: MIT
Project-URL: Homepage, https://github.com/xychenmsn/rotating-mitmproxy
Project-URL: Documentation, https://github.com/xychenmsn/rotating-mitmproxy#readme
Project-URL: Repository, https://github.com/xychenmsn/rotating-mitmproxy
Project-URL: Bug Tracker, https://github.com/xychenmsn/rotating-mitmproxy/issues
Project-URL: Changelog, https://github.com/xychenmsn/rotating-mitmproxy/blob/main/CHANGELOG.md
Keywords: proxy,mitmproxy,rotation,load-balancing,web-scraping,http-proxy,proxy-server
Classifier: Development Status :: 4 - Beta
Classifier: Intended Audience :: Developers
Classifier: License :: OSI Approved :: MIT License
Classifier: Operating System :: OS Independent
Classifier: Programming Language :: Python :: 3
Classifier: Programming Language :: Python :: 3.8
Classifier: Programming Language :: Python :: 3.9
Classifier: Programming Language :: Python :: 3.10
Classifier: Programming Language :: Python :: 3.11
Classifier: Programming Language :: Python :: 3.12
Classifier: Topic :: Internet :: Proxy Servers
Classifier: Topic :: Internet :: WWW/HTTP
Classifier: Topic :: Software Development :: Libraries :: Python Modules
Classifier: Topic :: System :: Networking
Requires-Python: >=3.8
License-File: LICENSE
Requires-Dist: mitmproxy>=10.0.0
Requires-Dist: click>=8.0.0
Requires-Dist: colorama>=0.4.0
Requires-Dist: requests>=2.25.0
Provides-Extra: dev
Requires-Dist: pytest>=7.0.0; extra == "dev"
Requires-Dist: pytest-cov>=4.0.0; extra == "dev"
Requires-Dist: pytest-asyncio>=0.21.0; extra == "dev"
Requires-Dist: black>=22.0.0; extra == "dev"
Requires-Dist: isort>=5.10.0; extra == "dev"
Requires-Dist: flake8>=5.0.0; extra == "dev"
Requires-Dist: mypy>=1.0.0; extra == "dev"
Requires-Dist: pre-commit>=2.20.0; extra == "dev"
Provides-Extra: docs
Requires-Dist: mkdocs>=1.4.0; extra == "docs"
Requires-Dist: mkdocs-material>=8.5.0; extra == "docs"
Requires-Dist: mkdocstrings[python]>=0.19.0; extra == "docs"
Provides-Extra: test
Requires-Dist: pytest>=7.0.0; extra == "test"
Requires-Dist: pytest-cov>=4.0.0; extra == "test"
Requires-Dist: pytest-asyncio>=0.21.0; extra == "test"
Requires-Dist: requests-mock>=1.9.0; extra == "test"
Dynamic: license-file
